odoo/addons/stock_picking_assign_serial_final/README.rst
odoo/addons/stock_picking_assign_serial_final/__init__.py
odoo/addons/stock_picking_assign_serial_final/__manifest__.py
odoo/addons/stock_picking_assign_serial_final/i18n/es.po
odoo/addons/stock_picking_assign_serial_final/i18n/stock_picking_assign_serial_final.pot
odoo/addons/stock_picking_assign_serial_final/models/__init__.py
odoo/addons/stock_picking_assign_serial_final/models/assign_serial_final_mixin.py
odoo/addons/stock_picking_assign_serial_final/models/stock_move.py
odoo/addons/stock_picking_assign_serial_final/readme/CONTRIBUTORS.rst
odoo/addons/stock_picking_assign_serial_final/readme/DESCRIPTION.rst
odoo/addons/stock_picking_assign_serial_final/readme/USAGE.rst
odoo/addons/stock_picking_assign_serial_final/static/description/icon.png
odoo/addons/stock_picking_assign_serial_final/static/description/index.html
odoo/addons/stock_picking_assign_serial_final/tests/__init__.py
odoo/addons/stock_picking_assign_serial_final/tests/common.py
odoo/addons/stock_picking_assign_serial_final/tests/test_stock_picking_assign_serial_final.py
odoo/addons/stock_picking_assign_serial_final/wizards/__init__.py
odoo/addons/stock_picking_assign_serial_final/wizards/stock_assign_serial_numbers.py
odoo/addons/stock_picking_assign_serial_final/wizards/stock_assign_serial_views.xml
odoo13_addon_stock_picking_assign_serial_final-13.0.1.1.1.dist-info/METADATA
odoo13_addon_stock_picking_assign_serial_final-13.0.1.1.1.dist-info/WHEEL
odoo13_addon_stock_picking_assign_serial_final-13.0.1.1.1.dist-info/top_level.txt
odoo13_addon_stock_picking_assign_serial_final-13.0.1.1.1.dist-info/RECORD
